betabernsum/__init__.py
betabernsum/bbs.py
betabernsum/bbs_test.py
betabernsum/probability_mass.py
betabernsum/region.py
betabernsum-0.1.3.dist-info/LICENSE
betabernsum-0.1.3.dist-info/METADATA
betabernsum-0.1.3.dist-info/WHEEL
betabernsum-0.1.3.dist-info/top_level.txt
betabernsum-0.1.3.dist-info/RECORD
