Metadata-Version: 2.1
Name: betabernsum
Version: 0.1.3
Summary: Sums of beta-bernoulli random variables
Home-page: https://gitlab.com/aaylward/betabernsum
Author: Anthony Aylward
Author-email: aaylward@salk.edu
License: UNKNOWN
Platform: UNKNOWN
Classifier: Programming Language :: Python :: 3
Classifier: License :: OSI Approved :: MIT License
Classifier: Operating System :: OS Independent
License-File: LICENSE
Requires-Dist: accelasc
Requires-Dist: scipy
